{
  "lastUpdated": "2025-08-14T00:00:25.288Z",
  "stats": {
    "users": {
      "count": 70740,
      "change": 7
    },
    "revenue": {
      "amount": 344536,
      "change": 4.7
    },
    "projects": {
      "count": 369,
      "change": -3
    },
    "tasks": {
      "count": 2563,
      "change": 13.6
    }
  },
  "activities": [
    {
      "type": "user",
      "title": "Task assigned",
      "timestamp": "2025-08-14T00:00:25.288Z"
    },
    {
      "type": "alert",
      "title": "Project milestone reached",
      "timestamp": "2025-08-13T00:00:45.017Z"
    },
    {
      "type": "user",
      "title": "Project created",
      "timestamp": "2025-08-12T00:00:38.594Z"
    },
    {
      "type": "message",
      "title": "Invoice generated",
      "timestamp": "2025-08-11T00:00:45.036Z"
    },
    {
      "type": "message",
      "title": "New user registered",
      "timestamp": "2025-08-10T00:00:06.059Z"
    }
  ],
  "weeklyActivity": [
    {
      "day": "Mon",
      "value": 14
    },
    {
      "day": "Tue",
      "value": 31
    },
    {
      "day": "Wed",
      "value": 83
    },
    {
      "day": "Thu",
      "value": 20
    },
    {
      "day": "Fri",
      "value": 16
    },
    {
      "day": "Sat",
      "value": 30
    },
    {
      "day": "Sun",
      "value": 34
    }
  ],
  "performanceMetrics": [
    {
      "date": "2023-11-03",
      "value": 26
    },
    {
      "date": "2023-11-04",
      "value": 35
    },
    {
      "date": "2023-11-05",
      "value": 27
    },
    {
      "date": "2023-11-06",
      "value": 44
    },
    {
      "date": "2023-11-07",
      "value": 44
    },
    {
      "date": "2023-11-08",
      "value": 40
    },
    {
      "date": "2023-11-09",
      "value": 25
    }
  ]
}